odoo10_addon_website_anchor_smooth_scroll-10.0.1.0.0-py2.7-nspkg.pth
odoo/addons/website_anchor_smooth_scroll/README.rst
odoo/addons/website_anchor_smooth_scroll/__init__.py
odoo/addons/website_anchor_smooth_scroll/__manifest__.py
odoo/addons/website_anchor_smooth_scroll/demo/website_anchor_smooth_scroll.xml
odoo/addons/website_anchor_smooth_scroll/i18n/bg.po
odoo/addons/website_anchor_smooth_scroll/i18n/de.po
odoo/addons/website_anchor_smooth_scroll/i18n/es.po
odoo/addons/website_anchor_smooth_scroll/i18n/fr.po
odoo/addons/website_anchor_smooth_scroll/i18n/it.po
odoo/addons/website_anchor_smooth_scroll/i18n/pt_BR.po
odoo/addons/website_anchor_smooth_scroll/i18n/sl.po
odoo/addons/website_anchor_smooth_scroll/static/description/icon.png
odoo/addons/website_anchor_smooth_scroll/static/src/js/website_anchor_smooth_scroll.js
odoo/addons/website_anchor_smooth_scroll/views/website_anchor_smooth_scroll.xml
odoo10_addon_website_anchor_smooth_scroll-10.0.1.0.0.dist-info/DESCRIPTION.rst
odoo10_addon_website_anchor_smooth_scroll-10.0.1.0.0.dist-info/METADATA
odoo10_addon_website_anchor_smooth_scroll-10.0.1.0.0.dist-info/RECORD
odoo10_addon_website_anchor_smooth_scroll-10.0.1.0.0.dist-info/WHEEL
odoo10_addon_website_anchor_smooth_scroll-10.0.1.0.0.dist-info/metadata.json
odoo10_addon_website_anchor_smooth_scroll-10.0.1.0.0.dist-info/namespace_packages.txt
odoo10_addon_website_anchor_smooth_scroll-10.0.1.0.0.dist-info/top_level.txt
