Metadata-Version: 2.0
Name: odoo10-addon-website-anchor-smooth-scroll
Version: 10.0.1.0.0
Summary: Replace default behavior for internal links (anchor only) with smooth scroll
Home-page: http://www.antiun.com
Author: Antiun Ingeniería S.L., Tecnativa, LasLabs, Odoo Community Association (OCA)
Author-email: support@odoo-community.org
License: AGPL-3
Platform: UNKNOWN
Classifier: Programming Language :: Python :: 2.7
Classifier: Framework :: Odoo
Classifier: License :: OSI Approved :: GNU Affero General Public License v3
Requires-Dist: odoo (<10.1dev,>=10.0)
